Classfile /home/shashin/projects/vasco-ci/vasco/test-classes/partials/boosted/Main.class
  Last modified 18 Jul, 2022; size 360 bytes
  MD5 checksum 92083ce6cfcb7cf1ca216eca96fe91f7
  Compiled from "Main.java"
class Main
  minor version: 0
  major version: 52
  flags: ACC_SUPER
Constant pool:
   #1 = Utf8               Main
   #2 = Class              #1             // Main
   #3 = Utf8               java/lang/Object
   #4 = Class              #3             // java/lang/Object
   #5 = Utf8               Main.java
   #6 = Utf8               <init>
   #7 = Utf8               ()V
   #8 = NameAndType        #6:#7          // "<init>":()V
   #9 = Methodref          #4.#8          // java/lang/Object."<init>":()V
  #10 = Utf8               main
  #11 = Utf8               ([Ljava/lang/String;)V
  #12 = Utf8               A
  #13 = Class              #12            // A
  #14 = Methodref          #13.#8         // A."<init>":()V
  #15 = Utf8               C
  #16 = Class              #15            // C
  #17 = Utf8               foo
  #18 = Utf8               (LA;LA;)LB;
  #19 = NameAndType        #17:#18        // foo:(LA;LA;)LB;
  #20 = Methodref          #16.#19        // C.foo:(LA;LA;)LB;
  #21 = Utf8               Code
  #22 = Utf8               LineNumberTable
  #23 = Utf8               SourceFile
{
  Main();
    descriptor: ()V
    flags:
    Code:
      stack=1, locals=1, args_size=1
         0: aload_0
         1: invokespecial #9                  // Method java/lang/Object."<init>":()V
         4: return
      LineNumberTable:
        line 1: 0
        line 1: 1
        line 1: 4

  public static void main(java.lang.String[]);
    descriptor: ([Ljava/lang/String;)V
    flags: ACC_PUBLIC, ACC_STATIC
    Code:
      stack=3, locals=1, args_size=1
         0: new           #13                 // class A
         3: dup
         4: invokespecial #14                 // Method A."<init>":()V
         7: new           #13                 // class A
        10: dup
        11: invokespecial #14                 // Method A."<init>":()V
        14: invokestatic  #20                 // Method C.foo:(LA;LA;)LB;
        17: pop
        18: return
      LineNumberTable:
        line 3: 0
        line 3: 3
        line 3: 4
        line 4: 7
        line 4: 10
        line 4: 11
        line 7: 14
        line 7: 17
        line 8: 18
}
SourceFile: "Main.java"
