Classfile /home/shashin/Documents/projects/vasco/test-classes/interproc/Main.class
  Last modified 22 Feb, 2022; size 741 bytes
  MD5 checksum 1a81f9273fb35b757f76b8d97c9f9345
  Compiled from "Main.java"
class Main
  minor version: 0
  major version: 52
  flags: ACC_SUPER
Constant pool:
   #1 = Methodref          #11.#42        // java/lang/Object."<init>":()V
   #2 = Class              #43            // A
   #3 = Methodref          #2.#42         // A."<init>":()V
   #4 = Class              #44            // B
   #5 = Methodref          #4.#42         // B."<init>":()V
   #6 = Class              #45            // C
   #7 = Methodref          #6.#42         // C."<init>":()V
   #8 = Methodref          #2.#46         // A.foo:(LB;LC;)LD;
   #9 = Methodref          #47.#48        // D.bar:()V
  #10 = Class              #49            // Main
  #11 = Class              #50            // java/lang/Object
  #12 = Utf8               <init>
  #13 = Utf8               ()V
  #14 = Utf8               Code
  #15 = Utf8               LineNumberTable
  #16 = Utf8               LocalVariableTable
  #17 = Utf8               this
  #18 = Utf8               LMain;
  #19 = Utf8               main
  #20 = Utf8               ([Ljava/lang/String;)V
  #21 = Utf8               args
  #22 = Utf8               [Ljava/lang/String;
  #23 = Utf8               a
  #24 = Utf8               LA;
  #25 = Utf8               b1
  #26 = Utf8               LB;
  #27 = Utf8               b2
  #28 = Utf8               c
  #29 = Utf8               LC;
  #30 = Utf8               d
  #31 = Utf8               LD;
  #32 = Utf8               x
  #33 = Utf8               I
  #34 = Utf8               StackMapTable
  #35 = Class              #22            // "[Ljava/lang/String;"
  #36 = Class              #43            // A
  #37 = Class              #44            // B
  #38 = Class              #45            // C
  #39 = Class              #51            // D
  #40 = Utf8               SourceFile
  #41 = Utf8               Main.java
  #42 = NameAndType        #12:#13        // "<init>":()V
  #43 = Utf8               A
  #44 = Utf8               B
  #45 = Utf8               C
  #46 = NameAndType        #52:#53        // foo:(LB;LC;)LD;
  #47 = Class              #51            // D
  #48 = NameAndType        #54:#13        // bar:()V
  #49 = Utf8               Main
  #50 = Utf8               java/lang/Object
  #51 = Utf8               D
  #52 = Utf8               foo
  #53 = Utf8               (LB;LC;)LD;
  #54 = Utf8               bar
{
  Main();
    descriptor: ()V
    flags:
    Code:
      stack=1, locals=1, args_size=1
         0: aload_0
         1: invokespecial #1                  // Method java/lang/Object."<init>":()V
         4: return
      LineNumberTable:
        line 1: 0
      LocalVariableTable:
        Start  Length  Slot  Name   Signature
            0       5     0  this   LMain;

  public static void main(java.lang.String[]);
    descriptor: ([Ljava/lang/String;)V
    flags: ACC_PUBLIC, ACC_STATIC
    Code:
      stack=3, locals=7, args_size=1
         0: new           #2                  // class A
         3: dup
         4: invokespecial #3                  // Method A."<init>":()V
         7: astore_1
         8: new           #4                  // class B
        11: dup
        12: invokespecial #5                  // Method B."<init>":()V
        15: astore_2
        16: new           #4                  // class B
        19: dup
        20: invokespecial #5                  // Method B."<init>":()V
        23: astore_3
        24: new           #6                  // class C
        27: dup
        28: invokespecial #7                  // Method C."<init>":()V
        31: astore        4
        33: aload_1
        34: aload_2
        35: aload         4
        37: invokevirtual #8                  // Method A.foo:(LB;LC;)LD;
        40: astore        5
        42: aload         5
        44: invokevirtual #9                  // Method D.bar:()V
        47: aload_1
        48: aload_3
        49: aload         4
        51: invokevirtual #8                  // Method A.foo:(LB;LC;)LD;
        54: astore        5
        56: bipush        10
        58: istore        6
        60: iload         6
        62: ifle          73
        65: aload_3
        66: astore_2
        67: iinc          6, -1
        70: goto          60
        73: return
      LineNumberTable:
        line 3: 0
        line 4: 8
        line 5: 16
        line 6: 24
        line 8: 33
        line 9: 42
        line 11: 47
        line 13: 56
        line 14: 60
        line 15: 65
        line 16: 67
        line 18: 73
      LocalVariableTable:
        Start  Length  Slot  Name   Signature
            0      74     0  args   [Ljava/lang/String;
            8      66     1     a   LA;
           16      58     2    b1   LB;
           24      50     3    b2   LB;
           33      41     4     c   LC;
           42      32     5     d   LD;
           60      14     6     x   I
      StackMapTable: number_of_entries = 2
        frame_type = 255 /* full_frame */
          offset_delta = 60
          locals = [ class "[Ljava/lang/String;", class A, class B, class B, class C, class D, int ]
          stack = []
        frame_type = 12 /* same */
}
SourceFile: "Main.java"
