Classfile /home/shashin/vasco/test-classes/test23/Main.class
  Last modified 05-Aug-2021; size 987 bytes
  MD5 checksum 60cea2405321cfc128b0819fd499e47b
  Compiled from "Main.java"
class Main
  minor version: 0
  major version: 55
  flags: (0x0020) ACC_SUPER
  this_class: #18                         // Main
  super_class: #19                        // java/lang/Object
  interfaces: 0, fields: 0, methods: 2, attributes: 1
Constant pool:
   #1 = Methodref          #19.#49        // java/lang/Object."<init>":()V
   #2 = Class              #50            // A
   #3 = Methodref          #2.#49         // A."<init>":()V
   #4 = Class              #51            // C
   #5 = Methodref          #4.#49         // C."<init>":()V
   #6 = Class              #52            // B
   #7 = Methodref          #6.#49         // B."<init>":()V
   #8 = Class              #53            // D
   #9 = Methodref          #8.#49         // D."<init>":()V
  #10 = Class              #54            // G
  #11 = Methodref          #10.#49        // G."<init>":()V
  #12 = Fieldref           #2.#55         // A.f:LF;
  #13 = Class              #56            // F
  #14 = Methodref          #13.#49        // F."<init>":()V
  #15 = Fieldref           #6.#55         // B.f:LF;
  #16 = Fieldref           #4.#55         // C.f:LF;
  #17 = Fieldref           #8.#55         // D.f:LF;
  #18 = Class              #57            // Main
  #19 = Class              #58            // java/lang/Object
  #20 = Utf8               <init>
  #21 = Utf8               ()V
  #22 = Utf8               Code
  #23 = Utf8               LineNumberTable
  #24 = Utf8               LocalVariableTable
  #25 = Utf8               this
  #26 = Utf8               LMain;
  #27 = Utf8               main
  #28 = Utf8               ([Ljava/lang/String;)V
  #29 = Utf8               f1
  #30 = Utf8               LF;
  #31 = Utf8               f2
  #32 = Utf8               args
  #33 = Utf8               [Ljava/lang/String;
  #34 = Utf8               a
  #35 = Utf8               LA;
  #36 = Utf8               c
  #37 = Utf8               LC;
  #38 = Utf8               b
  #39 = Utf8               LB;
  #40 = Utf8               d
  #41 = Utf8               LD;
  #42 = Utf8               x
  #43 = Utf8               I
  #44 = Utf8               y
  #45 = Utf8               StackMapTable
  #46 = Class              #33            // "[Ljava/lang/String;"
  #47 = Utf8               SourceFile
  #48 = Utf8               Main.java
  #49 = NameAndType        #20:#21        // "<init>":()V
  #50 = Utf8               A
  #51 = Utf8               C
  #52 = Utf8               B
  #53 = Utf8               D
  #54 = Utf8               G
  #55 = NameAndType        #59:#30        // f:LF;
  #56 = Utf8               F
  #57 = Utf8               Main
  #58 = Utf8               java/lang/Object
  #59 = Utf8               f
{
  Main();
    descriptor: ()V
    flags: (0x0000)
    Code:
      stack=1, locals=1, args_size=1
         0: aload_0
         1: invokespecial #1                  // Method java/lang/Object."<init>":()V
         4: return
      LineNumberTable:
        line 2: 0
      LocalVariableTable:
        Start  Length  Slot  Name   Signature
            0       5     0  this   LMain;

  public static void main(java.lang.String[]);
    descriptor: ([Ljava/lang/String;)V
    flags: (0x0009) ACC_PUBLIC, ACC_STATIC
    Code:
      stack=2, locals=8, args_size=1
         0: new           #2                  // class A
         3: dup
         4: invokespecial #3                  // Method A."<init>":()V
         7: astore_1
         8: new           #4                  // class C
        11: dup
        12: invokespecial #5                  // Method C."<init>":()V
        15: astore_2
        16: new           #6                  // class B
        19: dup
        20: invokespecial #7                  // Method B."<init>":()V
        23: astore_3
        24: new           #8                  // class D
        27: dup
        28: invokespecial #9                  // Method D."<init>":()V
        31: astore        4
        33: bipush        100
        35: istore        5
        37: iload         5
        39: bipush        100
        41: if_icmple     62
        44: new           #10                 // class G
        47: dup
        48: invokespecial #11                 // Method G."<init>":()V
        51: astore        6
        53: aload_1
        54: aload         6
        56: putfield      #12                 // Field A.f:LF;
        59: goto          77
        62: new           #13                 // class F
        65: dup
        66: invokespecial #14                 // Method F."<init>":()V
        69: astore        6
        71: aload_1
        72: aload         6
        74: putfield      #12                 // Field A.f:LF;
        77: iload         5
        79: ifle          113
        82: aload_3
        83: aload_1
        84: getfield      #12                 // Field A.f:LF;
        87: putfield      #15                 // Field B.f:LF;
        90: aload_2
        91: aload_3
        92: getfield      #15                 // Field B.f:LF;
        95: putfield      #16                 // Field C.f:LF;
        98: aload_1
        99: aload         4
       101: getfield      #17                 // Field D.f:LF;
       104: putfield      #12                 // Field A.f:LF;
       107: iinc          5, -1
       110: goto          77
       113: bipush        100
       115: istore        6
       117: iload         6
       119: bipush        100
       121: if_icmple     142
       124: new           #10                 // class G
       127: dup
       128: invokespecial #11                 // Method G."<init>":()V
       131: astore        7
       133: aload_1
       134: aload         7
       136: putfield      #12                 // Field A.f:LF;
       139: goto          157
       142: new           #13                 // class F
       145: dup
       146: invokespecial #14                 // Method F."<init>":()V
       149: astore        7
       151: aload_1
       152: aload         7
       154: putfield      #12                 // Field A.f:LF;
       157: iload         6
       159: ifle          193
       162: aload_3
       163: aload_1
       164: getfield      #12                 // Field A.f:LF;
       167: putfield      #15                 // Field B.f:LF;
       170: aload_2
       171: aload_3
       172: getfield      #15                 // Field B.f:LF;
       175: putfield      #16                 // Field C.f:LF;
       178: aload_1
       179: aload         4
       181: getfield      #17                 // Field D.f:LF;
       184: putfield      #12                 // Field A.f:LF;
       187: iinc          6, -1
       190: goto          157
       193: return
      LineNumberTable:
        line 6: 0
        line 7: 8
        line 8: 16
        line 9: 24
        line 11: 33
        line 12: 37
        line 13: 44
        line 14: 53
        line 15: 59
        line 17: 62
        line 18: 71
        line 22: 77
        line 23: 82
        line 24: 90
        line 25: 98
        line 27: 107
        line 31: 113
        line 32: 117
        line 33: 124
        line 34: 133
        line 35: 139
        line 37: 142
        line 38: 151
        line 42: 157
        line 43: 162
        line 44: 170
        line 45: 178
        line 47: 187
        line 49: 193
      LocalVariableTable:
        Start  Length  Slot  Name   Signature
           53       6     6    f1   LF;
           71       6     6    f2   LF;
          133       6     7    f1   LF;
          151       6     7    f2   LF;
            0     194     0  args   [Ljava/lang/String;
            8     186     1     a   LA;
           16     178     2     c   LC;
           24     170     3     b   LB;
           33     161     4     d   LD;
           37     157     5     x   I
          117      77     6     y   I
      StackMapTable: number_of_entries = 6
        frame_type = 255 /* full_frame */
          offset_delta = 62
          locals = [ class "[Ljava/lang/String;", class A, class C, class B, class D, int ]
          stack = []
        frame_type = 14 /* same */
        frame_type = 35 /* same */
        frame_type = 252 /* append */
          offset_delta = 28
          locals = [ int ]
        frame_type = 14 /* same */
        frame_type = 35 /* same */
}
SourceFile: "Main.java"
